setup.py
TSAndrey_Client.egg-info/PKG-INFO
TSAndrey_Client.egg-info/SOURCES.txt
TSAndrey_Client.egg-info/dependency_links.txt
TSAndrey_Client.egg-info/requires.txt
TSAndrey_Client.egg-info/top_level.txt
client/__init__.py
client/client.py
client/client/__init__.py
client/client/add_contact.py
client/client/client_db.py
client/client/del_contact.py
client/client/main_window.py
client/client/main_window_conv.py
client/client/start_window.py
client/client/transport.py