Metadata-Version: 1.0
Name: TSAndrey-Client
Version: 0.0.1
Summary: Messanger_Client
Home-page: UNKNOWN
Author: Tsimborevich Andrey
Author-email: siblp@mail.ru
License: UNKNOWN
Platform: UNKNOWN
